BrainNetAnno/__init__.py
BrainNetAnno/gene_celltype.py
BrainNetAnno/gene_layer.py
BrainNetAnno/mitochondrial.py
BrainNetAnno/mitochondrial_pls_cge.py
BrainNetAnno/neurotransmitter.py
BrainNetAnno/neurotransmitter_pls_cge.py
BrainNetAnno/transcriptome.py
BrainNetAnno/transcriptome_pls_cge.py
BrainNetAnno/utils.py
brainnetanno-0.1.0.dist-info/METADATA
brainnetanno-0.1.0.dist-info/WHEEL
brainnetanno-0.1.0.dist-info/top_level.txt
brainnetanno-0.1.0.dist-info/RECORD
