Metadata-Version: 2.4
Name: BrainNetAnno
Version: 0.1.0
Summary: A toolkit for molecular annotation of brain networks, integrating transcriptome, neurotransmitters, and mitochondria.
Home-page: https://github.com/Yunheng-Diao/BrainNetAnno
Author: Yunheng Diao
Author-email: Yunheng Diao <diaoyunheng@163.com>
License: MIT
Project-URL: Homepage, https://github.com/Yunheng-Diao/BrainNetAnno
Project-URL: Issues, https://github.com/Yunheng-Diao/BrainNetAnno/issues
Keywords: neuroscience,transcriptome,network,PLS,gene expression
Classifier: License :: OSI Approved :: MIT License
Classifier: Programming Language :: Python :: 3
Classifier: Programming Language :: Python :: 3 :: Only
Classifier: Programming Language :: Python :: 3.8
Classifier: Programming Language :: Python :: 3.9
Classifier: Programming Language :: Python :: 3.10
Classifier: Programming Language :: Python :: 3.11
Classifier: Intended Audience :: Science/Research
Classifier: Topic :: Scientific/Engineering :: Bio-Informatics
Requires-Python: >=3.8
Requires-Dist: numpy>=1.23
Requires-Dist: pandas>=2.0
Requires-Dist: scipy>=1.10
Requires-Dist: scikit-learn>=1.3
Requires-Dist: statsmodels>=0.14
Requires-Dist: matplotlib>=3.7
